iflowly/__init__.py
iflowly/__version__.py
iflowly/api.py
iflowly/auth.py
iflowly/client.py
iflowly/compat.py
iflowly/exceptions.py
iflowly/utils.py
iflowly-0.0.3.dist-info/METADATA
iflowly-0.0.3.dist-info/WHEEL
iflowly-0.0.3.dist-info/top_level.txt
iflowly-0.0.3.dist-info/RECORD
